{
    "lessons": [
        {
            "lesson": 1,
            "links": [
                {
                    "url": "http://juliehirschi.github.io/wdd230/holygrail.html",
                    "title": "Holy Grail Layout"
                }
            ]
        },
        {
            "lesson": 2,
            "links": [
                {
                    "url": "https://juliehirschi.github.io/wdd230/lesson02/design-principles.html",
                    "title": "Design Principles Document"
                },
                {
                    "url": "https://juliehirschi.github.io/wdd230/lesson02/media-query.html",
                    "title": "Design Media-Query"
                },
                {
                    "url": "https://juliehirschi.github.io/wdd230/lesson02/design.html",
                    "title": "Design"
                }
            ]
        },
        {
            "lesson": 3,
            "links": [
                {
                    "url": " ",
                    "title": "psuedo element"
                },
                {
                    "url": "https://codepen.io/JulieHirschi/pen/OJKNZPw",
                    "title": "responsive hamburger"
                },
                {
                    "url": " ",
                    "title": "combinator exercise"
                }
            ]
        },
        {
            "lesson": 4,
            "links": [
                {
                    "url": "https://codepen.io/JulieHirschi/pen/yyBBpyB",
                    "title": "psuedo class"
                }
            ]
        },
        {
            "lesson": 5,
            "links": [
                {
                    "url": "https://juliehirschi.github.io/wdd230/lesson05/bom.html",
                    "title": "BoM Dom Manipulation"
                }
            ]
        },
        {
            "lesson": 6,
            "links": [
                {
                    "url": "lesson06/images/landscape1.jpeg.webp",
                    "title": "WebP"
                },
                {
                    "url": "https://juliehirschi.github.io/wdd230/lesson06/responsive-images.html",
                    "title": "responsive images"
                }
            ]
        },
        {
            "lesson": 7,
            "links": [
                {
                    "url": "https://juliehirschi.github.io/wdd230/lesson07/lazyload.html",
                    "title": "lazyload image"
                },
                {
                    "url": "https://juliehirschi.github.io/wdd230/lesson07/bom.html",
                    "title": "BoM Local Storage"
                }
            ]
        },
        {
            "lesson": 8,
            "links": [
                {
                    "url": "https://juliehirschi.github.io/wdd230/lesson08/tablebuild.html",
                    "title": "Table Build"
                },
                {
                    "url": "https://juliehirschi.github.io/wdd230/lesson08/form.html",
                    "title": "HTML Form"
                },
                {
                    "url": " ",
                    "title": "Form"
                }
            ]
        },
        {
            "lesson": 9,
            "links": [
                {
                    "url": "https://juliehirschi.github.io/wdd230/lesson09/prophets.html",
                    "title": "Latter-Day Prophets"
                },
                {
                    "url": "https://juliehirschi.github.io/wdd230/lesson09/new-ward-members.json",
                    "title": "New Ward Members"
                }
            ]
        },
        {
            "lesson": 10,
            "links": [
                {
                    "url": "https://juliehirschi.github.io/wdd230/lesson10/weather.html",
                    "title": "Weather API"
                }
            ]
        }
    ]
}